AUTHORS
LICENSE
MANIFEST.in
README.rst
setup.py
datamaps/__init__.py
datamaps/admin.py
datamaps/lookups.py
datamaps/models.py
datamaps/fixtures/countries.json
datamaps/management/__init__.py
datamaps/management/commands/__init__.py
datamaps/management/commands/extract_countries.py
datamaps/management/commands/extract_scopes.py
datamaps/management/commands/get_coords.py
datamaps/migrations/0001_initial.py
datamaps/migrations/0002_auto__chg_field_scope_scale.py
datamaps/migrations/__init__.py
datamaps/static/datamaps/js/libs/d3/D3-LICENSE
datamaps/static/datamaps/js/libs/d3/d3.v3.min.js
datamaps/static/datamaps/js/libs/datamaps/LICENSE
datamaps/static/datamaps/js/libs/datamaps/datamaps.world.min.js
datamaps/static/datamaps/js/libs/topojson/LICENSE
datamaps/static/datamaps/js/libs/topojson/topojson.v1.min.js
datamaps/templates/datamaps/tags/libraries.html
datamaps/templates/datamaps/tags/scope_template.html
datamaps/templatetags/__init__.py
datamaps/templatetags/render_map.py
datamaps/tests/__init__.py
django_datamaps.egg-info/PKG-INFO
django_datamaps.egg-info/SOURCES.txt
django_datamaps.egg-info/dependency_links.txt
django_datamaps.egg-info/not-zip-safe
django_datamaps.egg-info/top_level.txt
example/core/__init__.py
example/core/urls.py
example/core/views.py
example/example/__init__.py
example/example/settings.py
example/example/urls.py
example/example/wsgi.py